params_flow/__init__.py
params_flow/layer.py
params_flow/model.py
params_flow/normalization.py
params_flow-0.0.4.dist-info/LICENSE
params_flow-0.0.4.dist-info/METADATA
params_flow-0.0.4.dist-info/WHEEL
params_flow-0.0.4.dist-info/top_level.txt
params_flow-0.0.4.dist-info/RECORD
